pubs/__init__.py
pubs/apis.py
pubs/bibstruct.py
pubs/color.py
pubs/command_utils.py
pubs/completion.py
pubs/content.py
pubs/databroker.py
pubs/datacache.py
pubs/endecoder.py
pubs/events.py
pubs/filebroker.py
pubs/p3.py
pubs/paper.py
pubs/plugins.py
pubs/pretty.py
pubs/pubs_cmd.py
pubs/query.py
pubs/repo.py
pubs/uis.py
pubs/update.py
pubs/utils.py
pubs/version.py
pubs/commands/__init__.py
pubs/commands/add_cmd.py
pubs/commands/bibtex_cmd.py
pubs/commands/conf_cmd.py
pubs/commands/doc_cmd.py
pubs/commands/edit_cmd.py
pubs/commands/export_cmd.py
pubs/commands/import_cmd.py
pubs/commands/init_cmd.py
pubs/commands/list_cmd.py
pubs/commands/note_cmd.py
pubs/commands/remove_cmd.py
pubs/commands/rename_cmd.py
pubs/commands/statistics_cmd.py
pubs/commands/tag_cmd.py
pubs/commands/url_cmd.py
pubs/commands/websearch_cmd.py
pubs/config/__init__.py
pubs/config/conf.py
pubs/config/spec.py
pubs/plugs/__init__.py
pubs/plugs/alias/__init__.py
pubs/plugs/alias/alias.py
pubs/plugs/git/__init__.py
pubs/plugs/git/git.py
pubs/templates/__init__.py
pubs/templates/str_templates.py
pubs-0.8.3.dist-info/METADATA
pubs-0.8.3.dist-info/WHEEL
pubs-0.8.3.dist-info/entry_points.txt
pubs-0.8.3.dist-info/top_level.txt
pubs-0.8.3.dist-info/RECORD
