Metadata-Version: 2.1
Name: pubs
Version: 0.8.3
Summary: command-line scientific bibliography manager
Home-page: https://github.com/pubs/pubs
Author: Fabien Benureau, Olivier Mangin, Jonathan Grizou
Author-email: fabien.benureau@gmail.com
Maintainer: Olivier Mangin
License: UNKNOWN
Platform: UNKNOWN
Classifier: Development Status :: 4 - Beta
Classifier: License :: OSI Approved :: GNU Lesser General Public License v3 (LGPLv3)
Classifier: Programming Language :: Python :: 2.7
Classifier: Programming Language :: Python :: 3
Classifier: Intended Audience :: Developers
Classifier: Intended Audience :: Science/Research
Requires-Dist: pyyaml
Requires-Dist: bibtexparser (>=1.0)
Requires-Dist: python-dateutil
Requires-Dist: six
Requires-Dist: requests
Requires-Dist: configobj
Requires-Dist: beautifulsoup4
Requires-Dist: feedparser
Provides-Extra: autocompletion
Requires-Dist: argcomplete ; extra == 'autocompletion'
